dialogy/__init__.py
dialogy/base/__init__.py
dialogy/base/entity_extractor/__init__.py
dialogy/base/input/__init__.py
dialogy/base/output/__init__.py
dialogy/base/plugin/__init__.py
dialogy/cli/__init__.py
dialogy/cli/project.py
dialogy/cli/workflow.py
dialogy/constants/__init__.py
dialogy/plugins/registry.py
dialogy/plugins/text/__init__.py
dialogy/plugins/text/address_parser/__init__.py
dialogy/plugins/text/address_parser/mapmyindia.py
dialogy/plugins/text/address_parser/maps.py
dialogy/plugins/text/calibration/__init__.py
dialogy/plugins/text/calibration/xgb.py
dialogy/plugins/text/canonicalization/__init__.py
dialogy/plugins/text/classification/__init__.py
dialogy/plugins/text/classification/mlp.py
dialogy/plugins/text/classification/retain_intent.py
dialogy/plugins/text/classification/tokenizers.py
dialogy/plugins/text/classification/xlmr.py
dialogy/plugins/text/combine_date_time/__init__.py
dialogy/plugins/text/dob_plugin/__init__.py
dialogy/plugins/text/duckling_plugin/__init__.py
dialogy/plugins/text/error_recovery/__init__.py
dialogy/plugins/text/error_recovery/error_recovery.py
dialogy/plugins/text/intent_entity_mutator/__init__.py
dialogy/plugins/text/intent_entity_mutator/actions_on_primitives.py
dialogy/plugins/text/intent_entity_mutator/const.py
dialogy/plugins/text/intent_entity_mutator/registry.py
dialogy/plugins/text/lb_plugin/__init__.py
dialogy/plugins/text/list_entity_plugin/__init__.py
dialogy/plugins/text/list_search_plugin/__init__.py
dialogy/plugins/text/list_search_plugin/sample_config.yaml
dialogy/plugins/text/merge_asr_output/__init__.py
dialogy/plugins/text/oos_filter/__init__.py
dialogy/plugins/text/qc_plugin/__init__.py
dialogy/plugins/text/slot_filler/__init__.py
dialogy/plugins/text/slot_filler/rule_slot_filler.py
dialogy/plugins/text/transliteration_plugin/__init__.py
dialogy/plugins/text/voting/__init__.py
dialogy/types/__init__.py
dialogy/types/entity/__init__.py
dialogy/types/entity/address/__init__.py
dialogy-2.2.5.dist-info/LICENSE.md
dialogy-2.2.5.dist-info/METADATA
dialogy-2.2.5.dist-info/WHEEL
dialogy-2.2.5.dist-info/entry_points.txt
dialogy-2.2.5.dist-info/RECORD
